setup.py
shared_clipboard/__init__.py
shared_clipboard/clipboard.py
shared_clipboard.egg-info/PKG-INFO
shared_clipboard.egg-info/SOURCES.txt
shared_clipboard.egg-info/dependency_links.txt
shared_clipboard.egg-info/requires.txt
shared_clipboard.egg-info/top_level.txt