Metadata-Version: 1.1
Name: shared-clipboard
Version: 0.0.1
Summary: Classes for saving, retrieving and clearing shared clipboards stored in Fluidinfo.
Home-page: https://github.com/fluidinfo/shared-clipboard
Author: Fluidinfo Inc.
Author-email: info@fluidinfo.com
License: UNKNOWN
Download-URL: https://github.com/fluidinfo/shared-clipboard
Keywords: twisted function retry
Platform: UNKNOWN
Classifier: Programming Language :: Python
Classifier: Development Status :: 4 - Beta
Classifier: Intended Audience :: Developers
Classifier: License :: OSI Approved :: Apache Software License
Classifier: Operating System :: OS Independent
Classifier: Topic :: Software Development :: Libraries :: Python Modules
Provides: shared_clipboard
